streams/FileStream.py
streams/Stream.py
streams/Transducer.py
streams/__init__.py
streams/data_checker.py
streams/generator_utilities.py
streams/utilities.py
streams/operations/__init__.py
streams/operations/operators.py
functional_streams-1.6.4.dist-info/LICENSE
functional_streams-1.6.4.dist-info/METADATA
functional_streams-1.6.4.dist-info/WHEEL
functional_streams-1.6.4.dist-info/top_level.txt
functional_streams-1.6.4.dist-info/RECORD
