Metadata-Version: 2.1
Name: functional-streams
Version: 1.6.4
Summary: Functional Programming Streams ,Similar like Java, for writing concise functions
Home-page: https://github.com/muthuishere/python-streams
Author: Muthukumaran Navaneethskrishnan
Author-email: muthuishere@gmail.com
License: UNKNOWN
Project-URL: Bug Tracker, https://github.com/muthuishere/python-streams/issues
Platform: UNKNOWN
Classifier: Programming Language :: Python :: 3
Classifier: License :: OSI Approved :: MIT License
Classifier: Operating System :: OS Independent
Requires-Python: >=3.6
License-File: LICENSE
